{
  "persons": [
    {
      "name": "Arto Hellas",
      "number": "040-123456",
      "id": 1
    },
    {
      "name": "Ada Lovelace",
      "number": "39-44-5323523",
      "id": 2
    },
    {
      "name": "Dan Abramov",
      "number": "12-43-234345",
      "id": 3
    },
    {
      "name": "Mary Poppendieck",
      "number": "39-23-6423122",
      "id": 4
    },
    {
      "name": "Tamanji Che",
      "number": "050-3333333",
      "id": 5
    },
    {
      "name": "moffi ebite",
      "number": "989-9309339",
      "id": 6
    },
    {
      "name": "Anna-Mari Halonen",
      "number": "90-989-898-30",
      "id": 7
    }
  ]
}